gemcall/__init__.py
gemcall/__main__.py
gemcall/gemcall.py
gemcall-0.9.2.dist-info/LICENSE
gemcall-0.9.2.dist-info/METADATA
gemcall-0.9.2.dist-info/WHEEL
gemcall-0.9.2.dist-info/entry_points.txt
gemcall-0.9.2.dist-info/top_level.txt
gemcall-0.9.2.dist-info/RECORD
