Metadata-Version: 2.1
Name: gemcall
Version: 0.9.2
Summary: A library and CLI tool for making gemini requests
Home-page: https://notabug.org/tinyrabbit/gemcall
Author: Björn Wärmedal
Author-email: bjorn.warmedal@gmail.com
License: MIT License
Classifier: Development Status :: 4 - Beta
Classifier: Intended Audience :: End Users/Desktop
Classifier: License :: OSI Approved :: MIT License
Classifier: Operating System :: POSIX :: Linux
Classifier: Programming Language :: Python :: 3
Classifier: Topic :: Internet
Classifier: Topic :: Software Development :: Libraries
Classifier: Topic :: Utilities
Classifier: Typing :: Typed
Requires-Python: >=3.9
License-File: LICENSE
Requires-Dist: pycryptodome
